[
    {
        "id" : 1,
        "name" : "sleep",
        "description" : "sleepy, sleepy time, time to go to sleep!",
        "revelation" : "but you never fall asleep...",
        "image" : "#daddad",
        "bonus" : 200,
        "completed" : false
    },
    {
        "id" : 2,
        "name" : "the other title",
        "description" : "the other description",
        "revelation" : "it has been revealed to you",
        "image" : "#aabbcc",
        "bonus" : 200,
        "completed" : false
    },
    {
        "id" : 3,
        "name" : "and another title",
        "description" : "with another description",
        "revelation" : "it has been revealed to you",
        "image" : "#ffbbcc",
        "bonus" : 200,
        "completed" : false
    },
    {
        "id" : 4,
        "name" : "yet another title",
        "description" : "and another description",
        "revelation" : "it has been revealed to you",
        "image" : "#abffbc",
        "bonus" : 200,
        "completed" : false
    },
    {
        "id" : 5,
        "name" : "Anamnesis",
        "description" : "You can't remember what anamnesis means",
        "revelation" : "well, you'll remember, probably.",
        "image" : "purple",
        "bonus" : 200,
        "completed" : false
    }
]